MANIFEST.in
setup.py
djangoproj/djangoapp.db
djangoproj/manage.py
djangoproj.egg-info/PKG-INFO
djangoproj.egg-info/SOURCES.txt
djangoproj.egg-info/dependency_links.txt
djangoproj.egg-info/requires.txt
djangoproj.egg-info/top_level.txt
djangoproj/djangoapp/__init__.py
djangoproj/djangoapp/__init__.pyc
djangoproj/djangoapp/admin.py
djangoproj/djangoapp/admin.pyc
djangoproj/djangoapp/editor.py
djangoproj/djangoapp/execute.py
djangoproj/djangoapp/fabfile.py
djangoproj/djangoapp/fabfile.pyc
djangoproj/djangoapp/models.py
djangoproj/djangoapp/models.pyc
djangoproj/djangoapp/newfile.txt
djangoproj/djangoapp/tests.py
djangoproj/djangoapp/views.py
djangoproj/djangoapp/views.pyc
djangoproj/djangoproj/__init__.py
djangoproj/djangoproj/__init__.pyc
djangoproj/djangoproj/settings.py
djangoproj/djangoproj/settings.pyc
djangoproj/djangoproj/urls.py
djangoproj/djangoproj/urls.pyc
djangoproj/djangoproj/wsgi.py
djangoproj/djangoproj/wsgi.pyc
djangoproj/form/__init__.py
djangoproj/form/__init__.pyc
djangoproj/form/admin.py
djangoproj/form/admin.pyc
djangoproj/form/forms.py
djangoproj/form/forms.pyc
djangoproj/form/models.py
djangoproj/form/models.pyc
djangoproj/form/tests.py
djangoproj/form/views.py
djangoproj/form/views.pyc
djangoproj/templates/base.html
djangoproj/templates/command.html
djangoproj/templates/contact.html
djangoproj/templates/copy.html
djangoproj/templates/createfile.html
djangoproj/templates/deletedir.html
djangoproj/templates/deletefile.html
djangoproj/templates/execute.html
djangoproj/templates/form.html
djangoproj/templates/hasil_post.html
djangoproj/templates/home.html
djangoproj/templates/makedir.html
djangoproj/templates/pilihan.html
djangoproj/templates/removedir.html
djangoproj/templates/search_form.html