Metadata-Version: 1.0
Name: djangoproj
Version: 0.3
Summary: mencoba
Home-page: UNKNOWN
Author: Anon
Author-email: UNKNOWN
License: UNKNOWN
Platform: UNKNOWN
